sasa_phys/smat_oparations.py
sasa_phys/stack.py
sasa_phys/star_product.py
sasa_phys-0.1.dist-info/METADATA
sasa_phys-0.1.dist-info/WHEEL
sasa_phys-0.1.dist-info/top_level.txt
sasa_phys-0.1.dist-info/RECORD
