Metadata-Version: 2.1
Name: sasa-phys
Version: 0.1
Summary: Semi Analytic Stacking Algorithm for Meta Surface stacks
Home-page: https://github.com/TimLucaTuran/SASA
Author: Tim Luca Turan, Max Bräuer
Author-email: timturan@web.de
License: MIT
Platform: UNKNOWN
Classifier: Programming Language :: Python :: 3
Classifier: License :: OSI Approved :: MIT License
Classifier: Operating System :: OS Independent
Requires-Dist: numpy
